m5_wrmsse/__init__.py
m5_wrmsse/aggregation.py
m5_wrmsse/gen_df_objs.py
m5_wrmsse/wrmsse.py
m5_wrmsse/data/__init__.py
m5_wrmsse/data/sales_ids.csv.gz
m5_wrmsse/data/test_agg.csv.gz
m5_wrmsse/data/train_mse.csv.gz
m5_wrmsse/data/weights.csv.gz
m5_wrmsse-1.0.0.dist-info/LICENSE
m5_wrmsse-1.0.0.dist-info/METADATA
m5_wrmsse-1.0.0.dist-info/WHEEL
m5_wrmsse-1.0.0.dist-info/top_level.txt
m5_wrmsse-1.0.0.dist-info/RECORD
