Metadata-Version: 2.1
Name: m5-wrmsse
Version: 1.0.0
Summary: WRMSSE score for the M5 dataset
Home-page: https://github.com/pmrgn/m5-wrmsse
Author: Paul Morgan
Author-email: 
License: Copyright (c) 2022, Paul Morgan        
Requires-Python: >=3.9
License-File: LICENSE
Requires-Dist: numpy (>=1.20)
Requires-Dist: pandas (>=1.2)
